LICENSE
MANIFEST.in
README.md
README.txt
setup.cfg
setup.py
tests/__init__.py
tests/conftest.py
tests/test_create_db.py
tests/test_import_data.py
tests/test_import_ddl.py
xplordb/__init__.py
xplordb/create_db.py
xplordb/import_data.py
xplordb/import_ddl.py
xplordb/minimal_dao.py
xplordb/schema.py
xplordb/sql_utils.py
xplordb.egg-info/PKG-INFO
xplordb.egg-info/SOURCES.txt
xplordb.egg-info/dependency_links.txt
xplordb.egg-info/requires.txt
xplordb.egg-info/top_level.txt
xplordb/datamodel/__init__.py
xplordb/datamodel/collar.py
xplordb/datamodel/dataset.py
xplordb/datamodel/lith.py
xplordb/datamodel/metadata.py
xplordb/datamodel/person.py
xplordb/datamodel/survey.py
xplordb/schema/assay/assay.sql
xplordb/schema/assay/functions/flat_method.sql
xplordb/schema/assay/functions/flat_ppm.sql
xplordb/schema/assay/functions/import.sql
xplordb/schema/assay/functions/structural_types.sql
xplordb/schema/assay/populate/assay.sql
xplordb/schema/assay/populate/batch.sql
xplordb/schema/assay/populate/flat_method.sql
xplordb/schema/assay/populate/flat_ppm.sql
xplordb/schema/assay/populate/raw.sql
xplordb/schema/assay/roles/grants.sql
xplordb/schema/assay/table/assay.sql
xplordb/schema/assay/table/batch.sql
xplordb/schema/assay/table/flat_method.sql
xplordb/schema/assay/table/flat_ppm.sql
xplordb/schema/assay/table/raw.sql
xplordb/schema/assay/views/assay.sql
xplordb/schema/assay/views/intercepts.sql
xplordb/schema/dem/dem.sql
xplordb/schema/dem/functions/alos_cap_update_example.sql
xplordb/schema/dem/functions/cap_alos_example.sql
xplordb/schema/dem/populate/capricorn.sql
xplordb/schema/dem/roles/grants.sql
xplordb/schema/dem/table/capricorn.sql
xplordb/schema/dh/dh.sql
xplordb/schema/dh/functions/check_depth_m.sql
xplordb/schema/dh/functions/check_from_m.sql
xplordb/schema/dh/functions/check_to_m.sql
xplordb/schema/dh/functions/dh_planned_trace.sql
xplordb/schema/dh/functions/dh_trace.sql
xplordb/schema/dh/functions/dog_leg.sql
xplordb/schema/dh/functions/geom_update_xyz.sql
xplordb/schema/dh/functions/get_planar_srid.sql
xplordb/schema/dh/functions/planned_loc_update_xyz.sql
xplordb/schema/dh/functions/planned_trace_update.sql
