Metadata-Version: 2.2
Name: xplordb
Version: 0.13.8
Summary: Python module to read/write data into xplordb database
Home-page: https://gitlab.com/geolandia/openlog/xplordb
Author: Oslandia
Author-email: geology@oslandia.com
License: AGPLv3
Classifier: Development Status :: 3 - Alpha
Classifier: Intended Audience :: Developers
Classifier: Programming Language :: Python :: 3.8
Requires-Python: >=3.8
License-File: LICENSE
Requires-Dist: psycopg2
Requires-Dist: chevron
Requires-Dist: sqlalchemy<2.0,>=1.4
Requires-Dist: GeoAlchemy2
Provides-Extra: dev
Requires-Dist: flake8; extra == "dev"
Requires-Dist: pytest; extra == "dev"
Requires-Dist: pytest-cov; extra == "dev"
Dynamic: author
Dynamic: author-email
Dynamic: classifier
Dynamic: description
Dynamic: description-content-type
Dynamic: home-page
Dynamic: license
Dynamic: provides-extra
Dynamic: requires-dist
Dynamic: requires-python
Dynamic: summary
